donb_gallery/__init__.py
donb_gallery/_pyinstaller_hook_dir.py
donb_gallery/hook-donb_gallery.py
donb_gallery/py.typed
donb_gallery/sphinx_examples.py
donb_gallery/types.py
donb_gallery/data/config_gallery.toml
donb_gallery/data/icons/drag.png
donb_gallery/data/icons/drag.xpm
donb_gallery/data/icons/filter.png
donb_gallery/data/icons/filter.xpm
donb_gallery/data/icons/folder.png
donb_gallery/data/icons/folder.xpm
donb_gallery/data/icons/forbidden.png
donb_gallery/data/icons/forbidden.xpm
donb_gallery/data/icons/minus.png
donb_gallery/data/icons/minus.xpm
donb_gallery/data/icons/plus.png
donb_gallery/data/icons/plus.xpm
donb_gallery/data/ui_files/cell_widget.ui
donb_gallery/data/ui_files/main_widget.ui
donb_gallery/data/ui_files/tab_widget.ui
donb_gallery/data/ui_files/tag_tree_widget.ui
donb_gallery/models/__init__.py
donb_gallery/models/gallery_models.py
donb_gallery/models/tags.py
donb_gallery/models/views.py
donb_gallery/widgets/__init__.py
donb_gallery/widgets/drag.py
donb_gallery/widgets/grid.py
donb_gallery/widgets/icons.py
donb_gallery/widgets/main_widget.py
donb_gallery/widgets/menus.py
donb_gallery/widgets/my_custom_gallery_widget.py
donb_gallery/widgets/query.py
donb_gallery/widgets/tag_tree.py
donb_gallery/widgets/widget_parameters.py
donb_gallery-1.0.2.dist-info/METADATA
donb_gallery-1.0.2.dist-info/WHEEL
donb_gallery-1.0.2.dist-info/entry_points.txt
donb_gallery-1.0.2.dist-info/top_level.txt
donb_gallery-1.0.2.dist-info/RECORD
