Metadata-Version: 2.1
Name: donb-gallery
Version: 1.0.2
Summary: A gallery QWidget for managing objects through tags
Home-page: UNKNOWN
Author: Don Beberto
Author-email: bebert64@gmail.com
License: UNKNOWN
Platform: UNKNOWN
Requires-Dist: Pyside6
Requires-Dist: donb-custom-widget
Requires-Dist: donb-tools
Requires-Dist: donb-config[toml]
Requires-Dist: peewee
